tcvectordb/__init__.py
tcvectordb/debug.py
tcvectordb/exceptions.py
tcvectordb/asyncapi/__init__.py
tcvectordb/asyncapi/client/__init__.py
tcvectordb/asyncapi/client/stub.py
tcvectordb/asyncapi/model/__init__.py
tcvectordb/asyncapi/model/ai_database.py
tcvectordb/asyncapi/model/collection.py
tcvectordb/asyncapi/model/collection_view.py
tcvectordb/asyncapi/model/database.py
tcvectordb/asyncapi/model/document_set.py
tcvectordb/client/__init__.py
tcvectordb/client/httpclient.py
tcvectordb/client/stub.py
tcvectordb/model/__init__.py
tcvectordb/model/ai_database.py
tcvectordb/model/atomic_function.py
tcvectordb/model/collection.py
tcvectordb/model/collection_view.py
tcvectordb/model/database.py
tcvectordb/model/document.py
tcvectordb/model/document_set.py
tcvectordb/model/enum.py
tcvectordb/model/index.py
tcvectordb/model/permission.py
tcvectordb/rpc/__init__.py
tcvectordb/rpc/client/__init__.py
tcvectordb/rpc/client/rpcclient.py
tcvectordb/rpc/client/stub.py
tcvectordb/rpc/client/vdbclient.py
tcvectordb/rpc/model/__init__.py
tcvectordb/rpc/model/collection.py
tcvectordb/rpc/model/database.py
tcvectordb/rpc/proto/__init__.py
tcvectordb/rpc/proto/olama_pb2.py
tcvectordb/rpc/proto/olama_pb2_grpc.py
tcvectordb/toolkit/__init__.py
tcvectordb/toolkit/binary.py
tests/__init__.py
tests/model/__init__.py
tests/model/test_collection.py
tests/model/test_document.py
tcvectordb-2.0.0.dist-info/LICENSE
tcvectordb-2.0.0.dist-info/METADATA
tcvectordb-2.0.0.dist-info/WHEEL
tcvectordb-2.0.0.dist-info/top_level.txt
tcvectordb-2.0.0.dist-info/RECORD
