Metadata-Version: 2.1
Name: tcvectordb
Version: 2.0.0
Summary: Tencent VectorDB Python SDK
Home-page: UNKNOWN
Author: tencent vdb team
License: UNKNOWN
Platform: UNKNOWN
Requires-Python: >=3
Requires-Dist: requests
Requires-Dist: cos-python-sdk-v5
Requires-Dist: grpcio
Requires-Dist: grpcio-tools
Requires-Dist: cachetools
Requires-Dist: urllib3
Requires-Dist: tcvdb-text
Requires-Dist: numpy
Requires-Dist: ujson
